{"DESENVOLVEDOR": 1040, "DE": 974, "A": 918, "E": 685, "END": 371, "PARA": 371, "EM": 330, "REMOTO": 319, "COM": 297, "DESENVOLVEDORES": 246, "PLENO": 243, "SÊNIOR": 232, "STACK": 215, "BACK": 214, "FULL": 213, "JAVA": 188, "VAGAS": 181, "SUPORTE": 167, "PESSOAS": 167, "FRONT": 160, "O": 158, "QUE": 158, "ANALISTA": 150, "UMA": 124, "TÉCNICO": 121, "SISTEMAS": 120, "EXPERIÊNCIA": 119, "COMO": 100, "REACT": 100, "DESENVOLVIMENTO": 92, "JS": 88, "DA": 84, "É": 84, "GEEKHUNTER": 82, "VOCÊ": 79, "INFORMÁTICA": 78, "UM": 77, "MOBILE": 77, "DESENVOLVEDORAS": 77, "NO": 76, "DO": 75, "PROGRAMADORES": 74, "NA": 72, "CONTRATAR": 72, "REQUISITOS": 70, "NET": 68, "C": 68, "PROGRAMADOR": 67, "NODE": 64, "GRANDES": 64, "CONHECIMENTO": 62, "PYTHON": 59, "MUITO": 59, "NOS": 57, "NOSSO": 56, "AS": 55, "OS": 55, "PHP": 54, "MAIS": 54, "POR": 52, "TI": 51, "JÁ": 48, "TER": 48, "OU": 47, "RUBY": 47, "DADOS": 46, "TELECOMUNICAÇÕES": 46, "SE": 45, "DEVOPS": 45, "TÉCNICOS": 44, "JAVASCRIPT": 44, "ESTAMOS": 44, "ANDROID": 43, "DAS": 43, "EMPRESA": 41, "AWS": 41, "NÃO": 41, "ARQUITETURA": 38, "TIME": 38, "SER": 38, "CAPACIDADE": 38, "SOBRE": 37, "VAGA": 36, "TEMOS": 36, "RESPONSABILIDADES": 34, "CLOUD": 34, "MAS": 34, "ISSO": 33, "AQUI": 33, "CONHECIMENTOS": 32, "DOS": 32, "AUTOMAÇÃO": 31, "TRANSFORMAR": 31, "AJUDAR": 31, "SABER": 31, "PROGRAMAÇÃO": 30, "2": 30, "PERFORMANCE": 30, "MUNDO": 30, "CORE": 29, "APAIXONADO": 29, "SOLUÇÕES": 29, "METODOLOGIAS": 29, "+": 29, "TECNOLOGIA": 28, "DURANTE": 28, "FOCO": 28, "SUPER": 28, "INFRAESTRUTURA": 27, "TRABALHAR": 27, "PROJETOS": 27, "APLICAÇÕES": 27, "PRECISAMOS": 27, "JÚNIOR": 26, "QUALIDADE": 26, "VAI": 26, "VALORIZAMOS": 26, "AUXILIAR": 26, "PESSOA": 25, "SOFTWARE": 25, "NAS": 25, "NATIVE": 25, "BANCOS": 25, "DANDO": 25, "PROCURANDO": 25, "100%": 25, "IOS": 24, "KOTLIN": 24, "S": 24, "ACABAR": 24, "SPAM": 24, "BRINCADEIRA": 24, "MISSÃO": 24, "COMPRA": 24, "ALGO": 24, "HUMANIZADO": 24, "INTELIGENTE": 24, "PODERES": 24, "VÊM": 24, "MINER": 24, "LIDAR": 24, "ESCALABILIDADE": 24, "MILHÕES": 24, "IMPACTADAS": 24, "MÊS": 24, "APRENDIZADO": 24, "ALGUÉM": 24, "CHEGUE": 24, "VOADORA": 24, "SABE": 24, "NÍVEL": 23, "RAILS": 23, "ANGULAR": 23, "ESPECIALISTA": 22, "SUA": 22, "ON": 22, "SQL": 21, "AMBIENTE": 21, "ATUAR": 21, "GOOGLE": 21, "NOSSOS": 21, "WEB": 20, "|": 20, "REDES": 20, "BLU": 20, "CONSULTOR": 20, "ALTA": 20, "LINUX": 20, "FRONTEND": 20, "SWIFT": 20, "REALIZAR": 20, "▫️": 20, "ANOS": 19, "DESAFIOS": 19, "NOVAS": 19, "OPORTUNIDADE": 19, "PARTE": 19, "PROCURAMOS": 19, "ÁGIL": 19, "TESTES": 19, "PROBLEMAS": 18, "SERÁ": 18, "INFORMAÇÃO": 18, "INTEGRAÇÃO": 18, "CLIENTE": 18, "WINDOWS": 18, "SÃO": 18, "MONITORAMENTO": 18, "CLIENTES": 17, "NOSSA": 17, "ATRAVÉS": 17, "CONHECER": 17, "ETC": 17, "MYSQL": 17, "DATA": 17, "ESPECIALISTAS": 17, "SR": 16, "TECNOLOGIAS": 16, "LINGUAGENS": 16, "QUER": 16, "VAREJO": 16, "DINÂMICO": 16, "ADMINISTRAÇÃO": 16, "VUE": 16, "EQUIPE": 16, "IMPLEMENTAÇÃO": 16, "DOCKER": 16, "OFFICE": 15, "INOVAÇÃO": 15, "INGLÊS": 15, "MERCADO": 15, "TEM": 15, "MANTER": 15, "IMPLANTAÇÃO": 15, "SEGURANÇA": 15, "NEGÓCIOS": 15, "HORÁRIO": 15, "SHELL": 15, "SCRIPT": 15, "MONGODB": 15, "PRINCIPAL": 15, "JENKINS": 15, "VIRTUALIZAÇÃO": 15, "OPERACIONAIS": 15, "P": 14, "BACKEND": 14, "HOME": 14, "MANUTENÇÃO": 14, "LINGUAGEM": 14, "PROFISSIONAIS": 14, "FERRAMENTAS": 14, "TENDÊNCIAS": 14, "TAMBÉM": 14, "FLUTTER": 14, "FULLSTACK": 14, "·": 14, "PRODUTOS": 14, "NÍVEIS": 14, "+200": 14, "CLUSTERS": 14, "GERENCIAR": 14, "S3": 14, "VPC": 14, "RDS": 14, "EC2": 14, "LB": 14, "EMR": 14, "REDSHIFT": 14, "CONTINUA": 14, "NEW": 14, "RELIC": 14, "ZABBIX": 14, "NAGIOS": 14, "POWERSHELL": 14, "–": 13, "SEJA": 13, "BRASIL": 13, "BUSCA": 13, "FLORIANÓPOLIS": 13, "TÉCNICA": 13, "STARTUP": 13, "CSS": 13, "PERFIL": 13, "GARANTIR": 13, "CONSULTORIA": 12, "PELA": 12, "TODO": 12, "RESOLVER": 12, "ESSA": 12, "[REMOTO]": 12, "TRAINEE": 12, "AVANÇADOS": 12, "TYPESCRIPT": 12, "SPRING": 12, "OBJETIVO": 12, "RESPONSÁVEL": 12, "FAZER": 11, "ARQUITETO": 11, "DESENVOLVEDORA": 11, "TIMES": 11, "UNIMED": 11, "QUALITY": 11, "ASSURANCE": 11, "•": 11, "ANÁLISE": 11, "AO": 11, "BEM": 11, "ENTREGA": 11, "SEMPRE": 11, "FLEXÍVEL": 11, "DIGITAIS": 11, "CULTURA": 11, "SUPERIOR": 10, "IRÁ": 10, "PROFISSIONAL": 10, "ENSINO": 10, "SISTEMA": 10, "DESEJÁVEL": 10, "PELO": 10, "PROCESSOS": 10, "{REMOTO}": 10, "@": 10, "DESCRIÇÃO": 10, "GOSTEM": 10, "AUTONOMIA": 10, "BUSQUEM": 10, "BENEFÍCIOS": 10, "MIL": 10, "RPA": 10, "PL": 10, "PAÍS": 10, "DEFINIDOS": 10, "WMS": 10, "LÍDER": 10, "ASP": 10, "SEU": 10, "DESENVOLVER": 10, "HTML": 10, "BOA": 10, "DJANGO": 10, "ORIENTADA": 10, "MELHOR": 10, "NEGÓCIO": 10, "MELHORIAS": 10, "NOVOS": 10, "PRODUTO": 10, "SP": 10, "PREOCUPAMOS": 10, "VESTE": 10, "NÉ": 10, "CRIATIVAS": 10, "DESPOJADO": 10, "POUCA": 10, "BUROCRACIA": 10, "FORMALIDADES": 10, "DÁ": 10, "OLHADA": 10, "FOTOS": 10, "SENTIR": 10, "VIBE": 10, "NERDS": 10, "+100": 10, "INTELIGENTES": 10, "BRINCAR": 10, "MINING": 10, "IA": 10, "VANILLA": 10, "NESTAS": 10, "ESTÁGIO": 9, "COLABORADOR": 9, "MANUTENÇÕES": 9, "MENOS": 9, "HABILIDADE": 9, "RESOLUÇÃO": 9, "FORMADO": 9, "UTILIZAÇÃO": 9, "DESENVOLVIDOS": 9, "4": 9, "3": 9, "APIS": 9, "PACOTE": 9, "VALE": 9, "TENHA": 9, "CONSIGA": 9, "EXISTENTES": 9, "OUTROS": 8, "FORMAÇÃO": 8, "INDÚSTRIA": 8, "PRESTAR": 8, "GOSTA": 8, "NÓS": 8, "ATRIBUIÇÕES": 8, "PRODUÇÃO": 8, "SENIOR": 8, "GRANDE": 8, "NODEJS": 8, "REST": 8, "CÓDIGO": 8, "ANALISAR": 8, "INTEGRAR": 8, "BANCO": 8, "AZURE": 8, "SOMOS": 8, "000": 8, "PRINCIPAIS": 8, "MELHORAR": 8, "ESTEJA": 8, "CONECTADA": 8, "TRANSPOR": 8, "PRODUZIDOS": 8, "CONSEQUENTEMENTE": 8, "FINAL": 8, "PÚBLICO": 8, "COORDENADORES": 8, "PROFESSORES": 8, "ALUNOS": 8, "COLABORADORES": 8, "INSTITUIÇÕES": 8, "UTILIZAM": 8, "WORKSPACE": 8, "TRANSFORMAÇÃO": 8, "ACADÊMICA": 8, "NOVO": 8, "FUNCIONALIDADES": 8, "CORREÇÕES": 8, "FUNCIONANDO": 8, "TAXA": 8, "OTIMIZAR": 8, "USABILIDADE": 8, "RESTANTE": 8, "CONTROLE": 7, "ÁREA": 7, "AVANÇADO": 7, "ESTÁ": 7, "QUEREMOS": 7, "ALTO": 7, "12": 7, "ESTRUTURAS": 7, "GARANTINDO": 7, "ATIVIDADES": 7, "USO": 7, "TRABALHO": 7, "CONSTRUIR": 7, "DAR": 7, "ATÉ": 7, "SC": 7, "IMPORTANTE": 7, "JR": 7, "PROCESSO": 7, "CURSO": 6, "ATENDENDO": 6, "GESTÃO": 6, "FINANCEIRO": 6, "BI": 6, "DEMANDAS": 6, "VENHA": 6, "ACREDITAMOS": 6, "INDEPENDENTE": 6, "ECONOMIA": 6, "TODA": 6, "CADEIA": 6, "SIMPLES": 6, "CURTE": 6, "TAMBÉM!": 6, "VOCÊ!": 6, "ATUAÇÃO": 6, "GRUPO": 6, "DEFINIÇÃO": 6, "COMERCIAL": 6, "ATUADO": 6, "SERVIÇOS": 6, "PROATIVO": 6, "SÓLIDO": 6, "FAMILIARIDADE": 6, "GERENCIAMENTO": 6, "KUBERNETES": 6, "GCP": 6, "COMPUTAÇÃO": 6, "CI": 6, "CD": 6, "FORTE": 6, "VIVÊNCIA": 6, "ENTRE": 6, "BUSCAMOS": 6, "PLATFORM": 6, "MICROSERVIÇOS": 6, "ORACLE": 6, "TRABALHANDO": 6, "BOOT": 6, "BUSCANDO": 6, "COMUNICAÇÃO": 6, "USUÁRIO": 6, "FUTURO": 6, "OUTRAS": 6, "ÁGEIS": 6, "NECESSÁRIO": 6, "BASE": 6, "GLOBAIS": 6, "HYBRIS": 6, "SEBASTIÃO": 6, "RD": 6, "SÓ": 6, "JUNIOR": 5, "TECH": 5, "QA": 5, "PROJETO": 5, "5": 5, "DOMÍNIO": 5, "SCRUM": 5, "VAGATECH": 5, "REVOLUCIONANDO": 5, "TEVE": 5, "ADMINISTRADOR": 5, "IDENTIFICA": 5, "CONTRIBUI": 5, "IDEIAS": 5, "MOVIMENTO": 5, "CASO": 5, "RESPOSTA": 5, "“SIM”": 5, "ENGENHEIRO": 5, "BLU!": 5, "VEMPRABLU": 5, "INSPIRAM": 5, "ENCONTRAR": 5, "ESTE": 5, "MESMO": 5, "PERFIL!": 5, "LEVE": 5, "DIVERTIDO": 5, "DESAFIADOR": 5, "FORÇA": 5, "MOTOR": 5, "TRABALHAMOS": 5, "DURO": 5, "TRANSFORMAÇÃO!": 5, "PROMOVEMOS": 5, "CONEXÃO": 5, "GERAMOS": 5, "IMPACTO": 5, "LOJISTAS": 5, "INDÚSTRIAS": 5, "ESTÃO": 5, "CONECTADAS": 5, "DIVERSOS": 5, "PLATAFORMA": 5, "LARAVEL": 5, "COMPLEXOS": 5, "INOVADORES": 5, "CRIATIVOS": 5, "SUAS": 5, "CARREIRAS": 5, "VIAFLOW": 5, "LUGAR": 5, "ESPECIAL": 5, "ESPERANDO": 5, "SEGUROS": 5, "SEGURADOR": 5, "BRAÇO": 5, "COOPERATIVAS": 5, "MÉDICAS": 5, "PRESENTE": 5, "DESENHAR": 5, "DOCUMENTOS": 5, "CRITÉRIOS": 5, "CONFIABILIDADE": 5, "DIRETRIZES": 5, "AVALIARÁ": 5, "POSSAM": 5, "UTILIZADAS": 5, "ATUARÁ": 5, "ENGENHARIA": 5, "FORMA": 5, "6": 5, "CRIATIVO": 5, "LEAD": 5, "10": 5, "LIDERAR": 5, "PROFICIÊNCIA": 5, "DESIGN": 5, "PRECISA": 5, "APRENDER": 5, "GIT": 5, "OBJETO": 5, "EVENTO": 5, "LEVANTAR": 5, "ELABORAR": 5, "ESPECIFICAÇÃO": 5, "PRESENCIAL": 5, "MAIORES": 5, "PRODUCT": 5, "1": 5, "OPERAÇÃO": 5, "MÃO": 5, "MASSA": 5, "CONHEÇA": 5, "FOCADA": 5, "SAP": 5, "COMUNICAR": 5, "ESCRITA": 5, "POSSUI": 5, "CENTENAS": 5, "ABERTAS": 5, "SALÁRIOS": 5, "R$": 5, "00": 5, "REMOTAMENTE": 5, "PRESENCIALMENTE": 5, "CAPITAIS": 5, "ESCOLHE": 5, "“OK": 5, "POIS": 5, "ESPERAMOS": 5, "PROGRAMMING": 5, "RJ": 5, "TREINAMENTO": 4, "COMPLETO": 4, "SOFTWARES": 4, "ÁREAS": 4, "DIFERENCIAL": 4, "C++": 4, "CONSTRUÇÃO": 4, "PRAZOS": 4, "SAAS": 4, "COMMERCE": 4, "INTELIGÊNCIA": 4, "SECURITY": 4, "NOVA": 4, "ZERO": 4, "GOSTE": 4, "BUSCAR": 4, "DIVIDIR": 4, "QUALIFICAÇÕES": 4, "9": 4, "ORIENTAÇÃO": 4, "8": 4, "HABILIDADES": 4, "UTILIZANDO": 4, "TRABALHADO": 4, "2+": 4, "MACHINE": 4, "LEARNING": 4, "GOLANG": 4, "ÀS": 4, "TÉCNICAS": 4, "NOSQL": 4, "INTERMEDIÁRIO": 4, "API": 4, "ENGINEER": 4, "DESAFIO": 4, "ESTRATÉGIA": 4, "MÍNIMO": 4, "CODE": 4, "UNIDADE": 4, "TENDO": 4, "SERVERLESS": 4, "EU": 4, "GANHO": 4, "ME": 4, "PLENOS": 4, "VALOR": 4, "CRESCER": 4, "ANO": 4, "ANTERIOR": 4, "AGÊNCIAS": 4, "PRODUTORAS": 4, "MARCAS": 4, "CLAREZA": 4, "VERBAL": 4, "PONTUALIDADE": 4, "COMPROMISSOS": 4, "EMBASAMENTO": 4, "TOMADA": 4, "DECISÕES": 4, "CONCLUÍDO": 4, "ALIMENTAÇÃO": 4, "REFEIÇÃO": 4, "MONTANDO": 4, "PRÁTICA": 4, "TERRAFORM": 4, "ANSIBLE": 4, "LOGS": 4, "CONTAINERS": 4, "ARRISCADO": 4, "NUVENS": 4, "PÚBLICAS": 4, "WS": 4, "BACANA!": 4, "POSSUIR": 4, "EXECUTOR": 4, "VÁRIOS": 4, "EXPERIÊNCIAS": 4, "CURTIR": 4, "COMPARTILHAR": 4, "CONSEGUIR": 4, "QUEBRAR": 4, "IMPEDIMENTOS": 4, "LONGO": 4, "CAMINHO": 4, "MODELO": 4, "CARGA": 4, "HORÁRIA": 4, "REMOTA": 4, "CONSUMIR": 4, "ENTENDER": 4, "CONSULTORES": 4, "PE": 4, "CE": 4, "BA": 4, "ENTRUST": 4, "PJ": 3, "PRÉ": 3, "METODOLOGIA": 3, "PLATAFORMAS": 3, "URA": 3, "CENTER": 3, "VENDAS": 3, "SOLUCIONAR": 3, "PAULO": 3, "PROGRAMAS": 3, "ARTIFICIAL": 3, "MELHORES": 3, "APLICATIVO": 3, "PADRÕES": 3, "JQUERY": 3, "NECESSÁRIOS": 3, "ENCAMINHAMENTO": 3, "AOS": 3, "AVANÇADA": 3, "REACTJS": 3, "MICRO": 3, "NOÇÕES": 3, "CIÊNCIA": 3, "SIMILARES": 3, "PREFERENCIALMENTE": 3, "D": 3, "TECNICO": 3, "DISPONIBILIDADE": 3, "SEGUIR": 3, "PRÁTICAS": 3, "CIA": 3, "DIFERENCIAIS": 3, "SÓLIDOS": 3, "EXPRESS": 3, "EE": 3, "CSS3": 3, "ELIXIR": 3, "*": 3, "CRIAR": 3, "SASS": 3, "SQLSPRING": 3, "HIBERNATEMAVENVUE": 3, "JSVUEX": 3, "VUETIFYNODEJSBANCO": 3, "POSTGRES": 3, "DRUPAL": 3, "BIG": 3, "ESTA": 3, "COMPREENDER": 3, "SATISFAÇÃO": 3, "GERAL": 3, "TDD": 3, "CONECTAR": 3, "WORDPRESS": 3, "ESPALHAR": 3, "SUSTENTABILIDADE": 3, "DESEJA": 3, "AGRICULTURA": 3, "SUSTENTÁVEL": 3, "RICO": 3, "ALINHA": 3, "INCENTIVOS": 3, "PLANETA": 3, "VAMOS": 3, "CONVERSAR!QUER": 3, "SERVIDORES": 3, "SEJAM": 3, "TAREFAS": 3, "GOSTAR": 3, "TODAS": 3, "SÊNIORES": 3, "CONSTRUINDO": 3, "VAGAESTAMOS": 3, "ATRIBUIÇÕESRESPONSÁVEL": 3, "ENTÃO": 3, "CRESCENDO": 3, "RECÉM": 3, "APRESENTAÇÃO": 3, "AMERICANA": 3, "MUNDIAL": 3, "SEGMENTO": 3, "ATUANDO": 3, "MANUFATURA": 3, "FINANCEIRAS": 3, "ENGINEERS": 3, "JRS": 3, "SR'S": 3, "LOCAIS": 3, "INSTITUIÇÃO": 3, "SERÃO": 3, "RESPONSÁVEIS": 3, "BANCARIA": 3, "SUSTENTANDO": 3, "DESENVOLVENDO": 3, "IMPULSIONARÃO": 3, "CRESCIMENTO": 3, "PONTA": 3, "ESTRUTURANDO": 3, "CONCEITO": 3, "MICROSERVICES": 3, "REFACTORING": 3, "FULLTIME": 3, "PANDEMIA": 3, "PARTTIME": 3, "APÓS": 3, "CONVERSAÇÃO": 3, "TERÁ": 3, "INTERAÇÃO": 3, "INTERNACIONAIS": 3, "ESTRATÉGICA": 3, "LED": 3, "GROWTH": 3, "PLG": 3, "VISA": 3, "GERADO": 3, "ENTRADA": 3, "STATION": 3, "LIGHT": 3, "INVERTIDO": 3, "TRADICIONAL": 3, "LEVAR": 3, "COMPRAR": 3, "DEPOIS": 3, "UTILIZADA": 3, "PLAYERS": 3, "CASES": 3, "SETOR": 3, "CONQUISTAMOS": 3, "ESSE": 3, "COMEÇO!": 3, "EMPOLGAR": 3, "APENAS": 3, "ESTAR": 3, "PRÓXIMO": 3, "ESTRATÉGIAS": 3, "EMPATIA": 3, "DELES": 3, "QUERER": 3, "INFOJOBS": 3, "SOCIAIS": 3, "ESCOPO": 3, "AUDITORIA": 2, "CURS": 2, "HELP": 2, "DESK": 2, "MÉDIO": 2, "PRÓPRIO": 2, "INSTALAÇÃO": 2, "CONFIGURAÇÃO": 2, "EQUIPAMENTOS": 2, "DATASUL": 2, "PROTHEUS": 2, "GRUPOS": 2, "CONTÍNUA": 2, "ARCHITECTURE": 2, "KANBAN": 2, "MARKETING": 2, "DIGITAL": 2, "ATENDIMENTO": 2, "ATENDER": 2, "FIBRAS": 2, "ÓPTICAS": 2, "CALL": 2, "VB": 2, "USUÁRIOS": 2, "INFRA": 2, "EXCLUSIVO": 2, "MULHERES": 2, "SEREM": 2, "EMPRESAS": 2, "0": 2, "ELETRÔNICA": 2, "VOLANTE": 2, "TESTE": 2, "SOC": 2, "TEAM": 2, "CIBERNÉTICAS": 2, "CRÉDITO": 2, "PORTO": 2, "ALEGRE": 2, "I": 2, "PERFURAÇÃO": 2, "APLICAÇÃO": 2, "SEUS": 2, "DESDE": 2, "SDK": 2, "USANDO": 2, "JUNIT": 2, "MOCKITO": 2, "ESPRESSO": 2, "ARQUITETURAIS": 2, "INTERFACE": 2, "BOOTSTRAP": 2, "DESENVOLV": 2, "HTML5": 2, "ESCREVER": 2, "ANALYTICS": 2, "BÁSICOS": 2, "BÁSICAS": 2, "PLENOREQUISITOS": 2, "ORIENTADO": 2, "GUIDELINES": 2, "UI": 2, "TECNOLOGI": 2, "VERSÃO": 2, "LEITURA": 2, "UWP": 2, "OBRIGATÓRIOS": 2, "TRANSITAMOS": 2, "LEGADOS": 2, "BLOCKCHAIN": 2, "ANTENADOS": 2, "FLEXÍVEIS": 2, "FRAMEWORK": 2, "PONTOS": 2, "UNITY3D": 2, "DEVE": 2, "UNITY": 2, "WEBGL": 2, "VR": 2, "VOLUME": 2, "INTEGRAÇÕES": 2, "ECOMMERCE": 2, "TERMOS": 2, "PRINCIPALMENTE": 2, "ORIENTADAS": 2, "OBJETOATUAÇÃO": 2, "FRAMEWORKS": 2, "JSVIVÊNCIA": 2, "RESTTER": 2, "RELACIONAIS": 2, "POSTGRSQL": 2, "LINDO": 2, "5+": 2, "SOMENTE": 2, "FAÇA": 2, "QUALIFICAÇÕESPROGRAMAÇÃO": 2, "CAPAZ": 2, "DOCUMENTAÇÕES": 2, "REPRODUÇÃO": 2, "MÍNIMA": 2, "ECOSSISTEMA": 2, "SPARK": 2, "GRAPHQL": 2, "BÁSICO": 2, "SERVICES": 2, "SERVER": 2, "CONTROLADOR": 2, "SRE": 2, "ESCALÁVEIS": 2, "SOLID": 2, "SOA": 2, "LOCAL": 2, "POSIÇÃO": 2, "VISANDO": 2, "TUDO": 2, "INTERNET": 2, "CRIANDO": 2, "PROGRAMANDO": 2, "TESTANDO": 2, "LEVANTAMENTO": 2, "SEGUINDO": 2, "EMBARCADO": 2, "DÚVIDAS": 2, "RELACIONAMENTO": 2, "POLÍTICAS": 2, "JOOMLA": 2, "AJUDAM": 2, "VIDAS!": 2, "ABAP": 2, "APEX": 2, "WORKFLOW": 2, "CIÊNCIAS": 2, "TÉCNICODIFERENCIAIS": 2, "CONTAM": 2, "FÁCIL": 2, "REDUX": 2, "COMPORTAMENTAIS": 2, "GO": 2, "VAGAQUER": 2, "PENSANDO": 2, "TORNAR": 2, "ALÉM": 2, "COLABORAR": 2, "ANSI": 2, "CLEAN": 2, "ANGULARJS": 2, "JEST": 2, "KAFKA": 2, "GATEWAY": 2, "QUESTIONAR": 2, "MENSURAR": 2, "TAMANHO": 2, "LÓGICA": 2, "CONSOLIDADA": 2, "AUTOGESTÃO": 2, "ESCRITÓRIO": 2, "EXPANDIR": 2, "ISTO": 2, "CADA": 2, "UNITÁRIOS": 2, "DEVELOPER": 2, "ZBRA": 2, "NECESSARIAMENTE": 2, "LISTADAS": 2, "DAMOS": 2, "APRENDA": 2, "CRESÇA": 2, "PARTICIPAR": 2, "API'S": 2, "EVENTOS": 2, "RIO": 2, "JANEIRO": 2, "PCD": 2, "PLENAS": 2, "15": 2, "CADASTRAN": 2, "FAZEMOS": 2, "REVIEW": 2, "PASSAR": 2, "PODENDO": 2, "MEIO": 2, "PAIR": 2, "MOB": 2, "BOM": 2, "HARDWARE": 2, "ELETRÔNICO": 2, "DOCUMENTAÇÃO": 2, "METEORJS": 2, "NECESSIDADES": 2, "DOCUMENTAR": 2, "&": 2, "AUXÍLIO": 2, "ANALISTAS": 2, "SD": 2, "MM": 2, "PÁGINA": 2, "MÍDIAS": 2, "ASSISTENTE": 2, "ACESSO": 2, "CONDUZIR": 2, "ACOMPANHAR": 2, "RHI": 2, "LEADER": 1, "NETCORE": 1, "FIRMWARE": 1, "LOJA": 1, "JUNDIAÍ": 1, "SETORES": 1, "OFERECIDO": 1, "INICIANTE": 1, "CURSO…": 1, "SENDO": 1, "PDV": 1, "RETAGUARDA": 1, "RESTAURANTES": 1, "WINDOWS…": 1, "IMPRESSORA": 1, "PREVENTIVAS": 1, "CORRETIVAS": 1, "IMPRESSÃO": 1, "DISPOSITIVOS": 1, "E…": 1, "REDE": 1, "CABEAMENTO": 1, "NESTLÉ": 1, "BOLSISTA": 1, "IEL": 1, "CNPQ": 1, "REQUISITO": 1, "TÍTULO": 1, "OBTIDO": 1, "ÚLTIMOS": 1, "MESTRE": 1, "IDIOMA": 1, "ENQUADRAR": 1, "SEGUINTES": 1, "COMPONENTS": 1, "INJEÇÃO": 1, "DEPENDÊNCIAS": 1, "BONS…": 1, "POWER": 1, "REFRIGERAÇÃO": 1, "ATRIBUIÇÕESDESENVOLVER": 1, "MUTANT": 1, "APLICANDO": 1, "XML": 1, "JSON": 1, "CHAMADAS": 1, "VOZ": 1, "SOLICITAÇÕES": 1, "AUTOATENDIMENTO": 1, "🚀": 1, "EFB_1043": 1, "GENESYS": 1, "ORIENTAR": 1, "QUANTO": 1, "CONTÁBEIS": 1, "IDENTIFICAR": 1, "CHAMADOS": 1, "UNOCRED": 1, "COBRANÇA": 1, "EIRELI": 1, "UNIX": 1, "REALIZADAS": 1, "RAMO": 1, "MINERAÇÃO": 1, "SIDERURGIA": 1, "CONTEXTO": 1, "INDUSTRIA": 1, "PESQUISA": 1, "SIMULAÇÃO": 1, "OTIMIZAÇÃO": 1, "EXECUÇÃO": 1, "COMPROMETIDO": 1, "CUSTOS": 1, "QUALIDA": 1, "WEBFORMS": 1, "275": 1, "GARANTIA": 1, "946": 1, "EQUIPES": 1, "CYBER": 1, "RED": 1, "BLUE": 1, "CONTRA": 1, "AMEAÇAS": 1, "PENTESTS": 1, "FORENSE": 1, "THREAT": 1, "HUNTING": 1, "PENTEST": 1, "OPERATION": 1, "WOASP": 1, "VULNERABILIDADES": 1, "REPAROS": 1, "343": 1, "17": 1, "143": 1, "ENFERMAGEM": 1, "60": 1, "COMPLEXIDADE": 1, "VOLTADAS": 1, "GEOLÓGICO": 1, "OPERACIONAL": 1, "POÇOS": 1, "PETROLÍFEROS": 1, "CONTROLAR": 1, "MONITORAR": 1, "PARÂMETROS": 1, "PRESTANDO": 1, "ASSISTÊNCIA": 1, "GEOLÓG": 1, "COMPRAS": 1, "TEMPORÁRIO": 1, "ROBÓTICAS": 1, "JORNADA": 1, "INOVAR": 1, "INVESTEM": 1, "JUNTE": 1, "APLICA": 1, "APOIAR": 1, "APLICATIVOS": 1, "DEBERÁ": 1, "PROATIVA": 1, "ENERGIA": 1, "GANAS": 1, "COLABORANDO": 1, "COMPANHEIROS": 1, "AUTOLAYOUT": 1, "CONSTRAINTS": 1, "BUILDER": 1, "THREADS": 1, "PROG": 1, "EVH_1071": 1, "ABRANGENTE": 1, "DOMINE": 1, "MS": 1, "POSTRESQL": 1, "CLÁSSICO": 1, "À": 1, "LEGADA": 1, "DESEJADO": 1, "AUTÔNOMO": 1, "AUTODIDATA": 1, "7": 1, "COMPREENSÃO": 1, "NATURALIDADE": 1, "BBB_1047": 1, "REQUISITOSEXPERIÊNCIA": 1, "LIDERANÇA": 1, "EQUIPESEXPERIÊNCIA": 1, "ÁGEISREQUISITOS": 1, "TÉCNICOSTER": 1, "CONCEITUAL": 1, "PARADIGMAS": 1, "ENDJAVASCRIPTREACTBACK": 1, "ENDNODE": 1, "JSARQUITETURA": 1, "RESTNOSQL": 1, "SQLDEVO": 1, "LIMPO": 1, "DOCUMENTADO": 1, "ELH_1019": 1, "DESENVOLVIMENTOPRÉ": 1, "CURSANDO": 1, "FINALIZANDO": 1, "ALGUMA": 1, "PROFICIENTE": 1, "ESTRUTURAÇÃO": 1, "SERVERL": 1, "IONIC": 1, "CORRELATAS": 1, "ÓTIMAS": 1, "ADOBE": 1, "SKETCH": 1, "INVISION": 1, "FIGMA": 1, "DETALHES": 1, "FOCADO": 1, "ENTREGAS": 1, "MATERIAL": 1, "HUMAN": 1, "GUID": 1, "DEV": 1, "PRA": 1, "MANDAR": 1, "NESSA": 1, "MANJAR": 1, "GRADUAÇÃO": 1, "PIPELINES": 1, "GITLAB": 1, "VONTADE": 1, "ENTREGÁVEIS": 1, "BASICO": 1, "CONJUNTO": 1, "PROTOCOLOS": 1, "TCP": 1, "IP": 1, "INGLES": 1, "COBOL": 1, "MICROSSERVIÇOS": 1, "BOAS": 1, "BASEADAS": 1, "APP": 1, "MODERNO": 1, "EQUIVALENTE": 1, "EXTRAS": 1, "COMPUT": 1, "3DSMAX": 1, "UNIVERSAL": 1, "INTERMEDIÁRIOS": 1, "XAML": 1, "PROTOCOL": 1, "CANDIDATO": 1, "CRIAT": 1, "3D": 1, "DEPLOY": 1, "PROTOCOLO": 1, "DICOM": 1, "RE": 1, "ES": 1, "VERSIONAMENTO": 1, "BASEADOS": 1, "BDD": 1, "QLIKVIEW": 1, "VTEXDESENVOLVEDOR": 1, "VTEX": 1, "HANDS": 1, "1+": 1, "2+OU": 1, "MORAR": 1, "QUANDO": 1, "VOLTARMOS": 1, "ENQUANTO": 1, "III": 1, "II": 1, "AMÉRICA": 1, "LATINA": 1, "EUA": 1, "EUROPA": 1, "NUM": 1, "CONTRATOS": 1, "ÂMBITO": 1, "NACIONAL": 1, "CRITICIDADE": 1, "QUALIFICAÇÕESTER": 1, "MAN": 1, "MANUTENCAO": 1, "MOBILETRABALHAR": 1, "JUNTO": 1, "UX": 1, "DESIGNERS": 1, "OWNERS": 1, "MANAGERS": 1, "DESENVOLVEDORESAUTONOMIA": 1, "LAYOUT": 1, "FIDELIDADE": 1, "JAVASCRIPTDOMÍNIO": 1, "VERS": 1, "ANSIHABILIDADES": 1, "NECESSÁRIAS": 1, "DESENVOLVIMENTOEXPERIÊNCIA": 1, "SEGUROSEXPERIÊNCIA": 1, "AT": 1, "CLOUDERA": 1, "HADOOP": 1, "PHYTON": 1, "PHYSPARK": 1, "HIVE": 1, "IMPALA": 1, "OBRIGATÓRIO": 1, "AUTOMATIZADOS": 1, "APOLLO": 1, "ASPNET": 1, "ENTITY": 1, "ADONET": 1, "POPPERJS": 1, "RXJS": 1, "DDL": 1, "DML": 1, "TCL": 1, "PROCEDURES": 1, "SELECT": 1, "VERSÕES": 1, "GITFLOW": 1, "SITE": 1, "RELIABILITY": 1, "SUSTENTAÇÃO": 1, "JUNTOS": 1, "FRANCA": 1, "EXPANSÃO": 1, "ROBUSTA": 1, "CONFIÁVEL": 1, "SÓLIDA": 1, "PRINCÍPIOS": 1, "SO": 1, "SUITE": 1, "BARRAMENTO": 1, "L": 1, "CAMPINAS": 1, "SAIBA": 1, "LEVANTAMENTOS": 1, "ORGANIZADO": 1, "PRÁTIC": 1, "HIERÁRQUICO": 1, "CANOAS": 1, "RS": 1, "POWERBUILDER": 1, "===&GT": 1, "OFERECE": 1, "OPORTUNIDADES": 1, "INTERNACIONALPROCURAMOS": 1, "ENGENHEIROS": 1, "RESULTADOS": 1, "FAZ": 1, "ALTAMENTE": 1, "MOTIVADO": 1, "SENTIDO": 1, "FIM": 1, "FEITO": 1, "ASSIM": 1, "ACORDO": 1, "FOI": 1, "DETERMINADO": 1, "RESPECTIVAMENTE": 1, "QUASE": 1, "PODE": 1, "ALGUM": 1, "FRAMEWORKDIFERENCIAL": 1, "YII": 1, "CLARA": 1, "ESCLARECER": 1, "PONTUAIS": 1, "CONTINGENCIAR": 1, "ERP": 1, "CIGAM": 1, "EFETIVO": 1, "ALINHADA": 1, "PLANEJAMENTO": 1, "HEY": 1, "SR!": 1, "ITENS": 1, "IMPORTANTES": 1, "CANDIDATAR": 1, "NATIVECONHECIMENTO": 1, "PUSH": 1, "NOTIFICATION": 1, "FIREB": 1, "CONTRATA": 1, "ORACLA": 1, "DEBUG": 1, "STANDARD": 1, "EXITS": 1, "BADIS": 1, "BAPIS": 1, "SMARTFORM": 1, "WEBDYNPRO": 1, "RFCS": 1, "IDOCS": 1, "NOTAS": 1, "EXIGIDOSHTML5": 1, "JSP": 1, "AJAXAPLICAÇÕES": 1, "MVCAPLICAÇÕES": 1, "ESCALÁVEISRESTFUL": 1, "JSONTESTES": 1, "UNITÁRIOSINGLÊS": 1, "BUILDS": 1, "AUTOMATIZADOSTOMCATAMBIENTE": 1, "AWSLINUXMETODOLOGIA": 1, "F": 1, "ASCENSÃO": 1, "EXIGIDOS": 1, "LEGADO": 1, "JAVA8": 1, "RELACIONAISCONTROLE": 1, "GITOPERAÇÕES": 1, "LINUXINGLÊS": 1, "PONTOSDESENVOLVIMENTO": 1, "RESTJAVAFXDOCKEREXPERIÊN": 1, "+2ATUAR": 1, "AGEISDESEJAVEL": 1, "COMPONENTIZAÇÃO": 1, "ONDE": 1, "COMPONENTES": 1, "CRIADOS": 1, "RESPONSIVO": 1, "IN": 1, "PROCESSADORES": 1, "LESS": 1, "JSX": 1, "SCALA": 1, "ACESS": 1, "MODELAGEM": 1, "PMO": 1, "RESILIENTES": 1, "FALHAS": 1, "DESENVOLVIDAS": 1, "UTILIZAND": 1, "QUEM": 1, "COLABORATIVO": 1, "PARTICIPARÁ": 1, "MULTIDISCIPLINAR": 1, "CRIARÁ": 1, "MULTINACIONAL": 1, "CONTATO": 1, "HTMLVENHA": 1, "AINDA": 1, "PERL": 1, "ENORME": 1, "ASPECTOS": 1, "ASSUMAM": 1, "POSTURA": 1, "TENHAM": 1, "DIFICULDADES": 1, "ENCARAR": 1, "ASSUMIR": 1, "AUTÔNOMAS": 1, "ACI": 1, "MELHORA": 1, "VIDA": 1, "FOMENTA": 1, "POTENCIALIZA": 1, "FABRICANTES": 1, "DISTRIBUIDORES": 1, "BENS": 1, "CONSUMO": 1, "HÁ": 1, "HOJE": 1, "80": 1, "SEDE": 1, "JOINVILLE": 1, "ACIMA": 1, "ENTREGAR": 1, "FEATURES": 1, "EXPERIÊNTES": 1, "ORIENTANDO": 1, "AJUDANDO": 1, "REVISANDO": 1, "SÊNIOROBRIGATÓRIO": 1, "GULP": 1, "WEBPACK": 1, "+TECH": 1, "UNITÁRIO": 1, "FACILIDADE": 1, "EBOA": 1, "HORA": 1, "ABERTA100%": 1, "TEMPO": 1, "INDETERMINADO": 1, "FERRAMENTA": 1, "CDC": 1, "CLOUDS": 1, "APLICAÇÒES": 1, "MATEMÁTICA": 1, "AFINSDISPONIBILIDADE": 1, "BUTANTÃ": 1, "ESFORÇADO": 1, "DESAFIOSCONSEGUIR": 1, "LEITUR": 1, "CRESCENDO!VAMOS": 1, "ABRIMOS": 1, "APESAR": 1, "GENTE": 1, "PROCURA": 1, "USAR": 1, "REACTEXPO": 1, "FLUENTE": 1, "3+": 1, "DESEJÁVEIS": 1, "MENSAGERIA": 1, "RABBITMQ": 1, "SQS": 1, "REDIS": 1, "CADASTRANDO": 1, "AÍ": 1, "”": 1, "&GT": 1, "PREFERÊNCIA": 1, "POSTGRESQL": 1, "U": 1, "RELACIONAL": 1, "SOAP": 1, "BAGAGEM": 1, "KUBERNETS": 1, "VISÃO": 1, "FILAS": 1, "BACKGROUND": 1, "GRAPHSQL": 1, "TAL": 1, "MILHARES": 1, "ATIVOS": 1, "!PARA": 1, "CONOSCO": 1, "BRILHANTES": 1, "ENTUSIASMADAS": 1, "CAMPOS": 1, "DESEJAM": 1, "AGREGAR": 1, "ELE": 1, "DESENVO": 1, "SENIORIDADES": 1, "14": 1, "CAD": 1, "ADORA": 1, "MEDO": 1, "TRÁFEGO": 1, "DOMINA": 1, "ORIENTADOS": 1, "RECENTE": 1, "MEGA": 1, "TALENTOSA": 1, "FUNÇÃO": 1, "LOGÍSTICO": 1, "INO": 1, "NOSSAS": 1, "INTERNAS": 1, "INTERNOS": 1, "LIGADOS": 1, "LINHA": 1, "CONTRIBUINDO": 1, "DIFERENTES": 1, "LINGUA": 1, "MATERNA": 1, "ARQUITETURAS": 1, "ESTUDADO": 1, "JETPACK": 1, "COMPONENTSCONHECER": 1, "UNITARIOSFICAREMOS": 1, "FELIZES": 1, "EXCLUSIVA": 1, "EVOLUIR": 1, "QUALIFIC": 1, "RELACIONADOS": 1, "TODOS": 1, "PRODUTOSREQUISITOS": 1, "QUALIFICAÇÕESREQUISITOS": 1, "DOMINIO": 1, "REAC": 1, "INTERESSANTE": 1, "CONHECIME": 1, "ZEND": 1, "MÉDIA": 1, "PROGRAMADOR1": 1, "VUECAPACIDADE": 1, "CONFIGURAR": 1, "TOTALMENTE": 1, "SOZINHOEXPERIÊNCIA": 1, "ACUMULADA": 1, "PORTFÓLIONÃO": 1, "PENSA": 1, "CÓDIGOS": 1, "LIGADO": 1, "BUSINESSORIENTA": 1, "JÚNIORENCONTRAR": 1, "BUGS": 1, "PROPOR": 1, "PLANOS": 1, "AÇÃODESEJÁVE": 1, "USAMOS": 1, "VOLTADA": 1, "JAVAS": 1, "JAVASC": 1, "SOFTWA": 1, "MONITORAMEN": 1, "CRM": 1, "ÀREA": 1, "NECES": 1, "NEGOCIOS": 1, "ESPERADO": 1, "PARCEIROS": 1, "REAIS": 1, "INTERAGIR": 1, "OUTR@S": 1, "STAKEHOLDERS": 1, "RITUAIS": 1, "—": 1, "STORAGE": 1, "BUILD": 1, "PUBLICAÇÃO": 1, "PLAY": 1, "DAGGER": 1, "RETROFIT": 1, "RXJAVA": 1, "RXKOTLIN": 1, "RXANDROID": 1, "ÚLTIMAS": 1, "PATTERNS": 1, "REACTIVE": 1, "BÔNUS": 1, "INFORMAÇÕES": 1, "ADICIONAIS": 1, "CONTRATAÇÃO": 1, "CLT": 1, "REMUNERAÇÃO": 1, "COMPETITIVA": 1, "VA": 1, "GYMPASS": 1, "UNIODONTO": 1, "SAÚDE": 1, "MENTAL": 1, "TESTER": 1, "EXTERNO": 1, "SUPRIMENTOS": 1, "TRILINGUE": 1, "EDTECH": 1, "CURITIBA": 1, "DEMOCRATIZAR": 1, "IDIOMAS": 1, "MUNDO!": 1, "VEZ": 1, "ATUAL": 1, "CONTEÚDOS": 1, "GRATUITOS": 1, "MUITA": 1, "AJUD": 1, "COMPUTADORES": 1, "PLANEJAR": 1, "CORPORATIVOS": 1, "CRIAÇÃO": 1, "CONCESSÃO": 1, "PRIVILÉGIOS": 1, "PERMISSÃO": 1, "MICROSOFT": 1, "ANALISANDO": 1, "VIABILIDADE": 1, "ENVIAR": 1, "DEMANDA": 1, "MINIMIZAR": 1, "LACUNAS": 1, "ENTENDIMENTO": 1, "EXECUÇ": 1, "TELECOM": 1, "FLORIANOPOLIS": 1, "COORDENAR": 1, "SERTÃO": 1, "SOB": 1, "RESPONSABILIDADE": 1, "REALIZAÇÃO": 1, "TRABALHOS": 1, "EXECUTADOS": 1, "FORMAS": 1, "PREVISTOS": 1, "ATUALIZAR": 1, "ADMINISTRAR": 1, "REPOSITÓRIOS": 1, "MODELOS": 1, "METADADOS": 1, "ORGANIZAÇÃO": 1, "ESPEC": 1, "CLIMA": 1, "DENTRO": 1, "ESTIMULANDO": 1, "CORRIGINDO": 1, "QUESTÕES": 1, "FORA": 1, "CONSIDERADOS": 1, "GERIR": 1, "RES": 1, "ELETRONICO": 1, "ATUALMENTE": 1, "ORGÃO": 1, "GOVERNAMENTAL": 1, "CENTRO": 1, "FLORIANÓPOLIS!": 1, "ESSENCIAIS": 1, "OBJETOS": 1, "DETALHAR": 1, "FAZE": 1, "EFETUAR": 1, "ANALISE": 1, "PREVENTIVA": 1, "CORRETIVA": 1, "PONTO": 1, "AUX": 1, "EXTERNA": 1, "DEMAIS": 1, "CARGO": 1, "COORDENADOR": 1, "IPLACE": 1, "SHOPPING": 1, "IGUATEMI": 1, "PROGRAMA": 1, "TECNICAMENTE": 1, "ESPERA": 1, "FLEXIBILIDADE": 1, "MANIPULAR": 1, "FONTES": 1, "DIVERSAS": 1, "PLANILHAS": 1, "RECRUTANDO": 1, "HYPER": 1, "V": 1, "ACTIVE": 1, "DIRECTORY": 1, "JAC": 1}